Workbook

Sheet ReadMe & Playbook
B2: MMD Recruit CRM — Customer Discovery Discovery Playbook
B4: 1. OVERVIEW OF THE CUSTOMER DISCOVERY TRACKER
B5: Purpose | C5: This tracker is designed for founder-led customer discovery. It helps aggregate qualitative feedback from 30 target customer interviews and convert them into quantitative metrics for product-market fit validation.
B6: Target Customers | C6: 1. Recruitment Agencies (Fastest-moving, credit card buyers) 2. MSMEs (Looking for simple, affordable HR systems) 3. Startup HR Teams (High growth, need integration capabilities)
B7: How to Use | C7: For every interview conducted, capture the raw notes using the Interview Notes Template, then fill in one row in the "Interview Tracker" tab. The tracker automatically calculates the Market Validation Score (MVS) for each lead.
B9: 2. MARKET VALIDATION SCORE (MVS) FORMULA
B10: Formula | C10: MVS = (Pain Intensity * 8) + (Urgency * 6) + (Budget/WTP Score * 4) + (Switching Probability Score * 2) Maximum score is 100. Column M in the tracker calculates this automatically using formulas.
B11: Pain Intensity (1-5) | C11: 1 = Nice-to-have problem. No real friction. 5 = Critical daily operational bottleneck (e.g., manual resume formatting taking 2 hours/day).
B12: Urgency (1-5) | C12: 1 = Happy to review in 6-12 months. No timeline. 5 = Need a solution immediately / ready to test next week.
B13: Budget/WTP Score (1-5) | C13: 1 = Free only / No budget. 5 = Has budget, currently spending money on software (e.g., Zoho/Bullhorn), willing to pay ₹2,500 - ₹8,000/mo.
B14: Switching Prob (1-5) | C14: 1 = Tied to an annual enterprise contract, will not switch. 5 = Extremely unhappy with current stack or on Excel, ready to switch today.
B16: 3. SCORE THRESHOLD INTERPRETATIONS
B17: MVS >= 75 (High Validation) | C17: Red-hot lead. Strong pain, high urgency, budget available, high switching probability. These should be prioritised for the 14-day Monday Beta Pilot cohort.
B18: MVS 50 - 74 (Moderate) | C18: Has the pain, but lacks urgency or authority to buy. Keep in the nurturing loop, but do not focus MVP roadmap on them.
B19: MVS < 50 (Low Validation) | C19: Usually enterprise HR teams or established agencies happy with their current stack. Do not build for them at this stage.

Sheet Interview Tracker
A1: Key Quotes / Feedback notes
A2: Fill out the details for each interview. Scores (I, J, K, L) are 1 to 5. MVS is calculated automatically (0-100). Scores >= 75 indicate high PMF validation.
A4: L-01 | B4: Rajesh Kumar | C4: Apex Staffing | D4: Recruitment Agency | E4: 3 | F4: Excel/Folders | G4: 0 | H4: Resume Formatting | I4: 5 | J4: 5 | K4: 5 | L4: 5 | M4: ==(I4*8)+(J4*6)+(K4*4)+(L4*2) | N4: Yes | O4: Resume Formatter | P4: 2500 | Q4: Committed | R4: 2026-06-08 | S4: Manual formatting takes 2 hrs/day. Very high interest in automated formatter.
A5: L-02 | B5: Priya Sharma | C5: TechRecruit | D5: Recruitment Agency | E5: 5 | F5: Zoho Recruit | G5: 6000 | H5: Slow Search | I5: 4 | J5: 4 | K5: 4 | L5: 4 | M5: ==(I5*8)+(J5*6)+(K5*4)+(L5*2) | N5: Yes | O5: Semantic Search | P5: 6000 | Q5: Committed | R5: 2026-06-08 | S5: Zoho search misses candidates inside older PDFs. Wants deep semantic keyword search.
A6: L-03 | B6: Amit Patel | C6: Global HR | D6: Recruitment Agency | E6: 15 | F6: Bullhorn | G6: 25000 | H6: UI Complexity | I6: 3 | J6: 2 | K6: 2 | L6: 1 | M6: ==(I6*8)+(J6*6)+(K6*4)+(L6*2) | N6: No | O6: None | P6: 0 | Q6: Not Interested | R6: 2026-06-09 | S6: Bullhorn is bloated, recruiters bypass it for Excel. Bound by annual contract, decision maker is external board.
A7: L-04 | B7: Vikram Malhotra | C7: Nexus Talent | D7: Recruitment Agency | E7: 4 | F7: Excel/Folders | G7: 0 | H7: Data Security | I7: 4 | J7: 4 | K7: 4 | L7: 5 | M7: ==(I7*8)+(J7*6)+(K7*4)+(L7*2) | N7: Yes | O7: Duplicate Alert | P7: 2000 | Q7: Committed | R7: 2026-06-09 | S7: Fear of recruiters leaving and stealing spreadsheet database. Eager to secure data.
A8: L-05 | B8: Shreya Sen | C8: Elite Executive | D8: Recruitment Agency | E8: 6 | F8: Freshteam | G8: 18000 | H8: Resume Formatting | I8: 4 | J8: 4 | K8: 4 | L8: 4 | M8: ==(I8*8)+(J8*6)+(K8*4)+(L8*2) | N8: Yes | O8: Resume Formatter | P8: 8000 | Q8: Interested | R8: 2026-06-10 | S8: Freshteam formatting takes too long, lacks automated templates. Willing to try a solution.
A9: L-06 | B9: Manish Sharma | C9: Pinnacle Staffing | D9: Recruitment Agency | E9: 3 | F9: Zoho Recruit | G9: 8000 | H9: Slow Search | I9: 5 | J9: 5 | K9: 5 | L9: 4 | M9: ==(I9*8)+(J9*6)+(K9*4)+(L9*2) | N9: Yes | O9: Auto-Match | P9: 8000 | Q9: Committed | R9: 2026-06-10 | S9: Wants candidate-to-job matching automation. Manually mapping takes hours. Ready to switch if matched.
A10: L-07 | B10: Kavita Rao | C10: Aspire Consulting | D10: Recruitment Agency | E10: 2 | F10: Excel/Folders | G10: 0 | H10: Resume Formatting | I10: 3 | J10: 3 | K10: 4 | L10: 5 | M10: ==(I10*8)+(J10*6)+(K10*4)+(L10*2) | N10: Yes | O10: Resume Formatter | P10: 1500 | Q10: Interested | R10: 2026-06-11 | S10: Copy-pasting details into Excel is tedious. WTP is lower, but high willingness to try beta.
A11: L-08 | B11: Rohan Das | C11: Vertex HR | D11: Recruitment Agency | E11: 8 | F11: Loxo | G11: 35000 | H11: Other | I11: 3 | J11: 3 | K11: 4 | L11: 3 | M11: ==(I11*8)+(J11*6)+(K11*4)+(L11*2) | N11: Yes | O11: Invoice Sync | P11: 7999 | Q11: Interested | R11: 2026-06-11 | S11: USD billing is fluctuating heavily in INR. Wants stable local invoicing. Worried about data migration downtime.
A12: L-09 | B12: Ananya Joshi | C12: Vantage Tech | D12: Recruitment Agency | E12: 5 | F12: Excel/Folders | G12: 0 | H12: Invoicing | I12: 4 | J12: 4 | K12: 4 | L12: 4 | M12: ==(I12*8)+(J12*6)+(K12*4)+(L12*2) | N12: Yes | O12: Invoice Sync | P12: 2500 | Q12: Committed | R12: 2026-06-12 | S12: Wants ATS linked to billing/invoicing directly when a placement is made.
A13: L-10 | B13: Deepak Nair | C13: Stellar Hire | D13: Recruitment Agency | E13: 12 | F13: Bullhorn | G13: 45000 | H13: UI Complexity | I13: 2 | J13: 2 | K13: 4 | L13: 1 | M13: ==(I13*8)+(J13*6)+(K13*4)+(L13*2) | N13: No | O13: None | P13: 0 | Q13: Not Interested | R13: 2026-06-12 | S13: Lacks easy syncing with WhatsApp/email, but switching is too high-friction for their team.
A14: L-11 | M14: ==(I14*8)+(J14*6)+(K14*4)+(L14*2)
A15: L-12 | M15: ==(I15*8)+(J15*6)+(K15*4)+(L15*2)
A16: L-13 | M16: ==(I16*8)+(J16*6)+(K16*4)+(L16*2)
A17: L-14 | M17: ==(I17*8)+(J17*6)+(K17*4)+(L17*2)
A18: L-15 | M18: ==(I18*8)+(J18*6)+(K18*4)+(L18*2)
A19: L-16 | M19: ==(I19*8)+(J19*6)+(K19*4)+(L19*2)
A20: L-17 | M20: ==(I20*8)+(J20*6)+(K20*4)+(L20*2)
A21: L-18 | M21: ==(I21*8)+(J21*6)+(K21*4)+(L21*2)
A22: L-19 | M22: ==(I22*8)+(J22*6)+(K22*4)+(L22*2)
A23: L-20 | M23: ==(I23*8)+(J23*6)+(K23*4)+(L23*2)
A24: L-21 | M24: ==(I24*8)+(J24*6)+(K24*4)+(L24*2)
A25: L-22 | M25: ==(I25*8)+(J25*6)+(K25*4)+(L25*2)
... A33: L-30 | M33: ==(I33*8)+(J33*6)+(K33*4)+(L33*2)

Sheet Discovery Dashboard
B2: MMD Recruit CRM — PMF Validation Dashboard
B4: METRIC DESCRIPTION | E4: SEGMENT SHARE & PAIN TRACKER
B5: Total Interviews Tracked | C5: ==COUNTIF('Interview Tracker'!B4:B33, "<>") | E5: Segment: Recruitment Agency | F5: ==COUNTIF('Interview Tracker'!D4:D33, "Recruitment Agency")
B6: High Validation Leads (MVS >= 75) | C6: ==COUNTIF('Interview Tracker'!M4:M33, ">=75") | E6: Segment: MSME | F6: ==COUNTIF('Interview Tracker'!D4:D33, "MSME")
B7: Average Pain Intensity (1-5) | C7: ==AVERAGE('Interview Tracker'!I4:I33) | E7: Segment: Startup HR | F7: ==COUNTIF('Interview Tracker'!D4:D33, "Startup HR")
B8: Average Urgency Score (1-5) | C8: ==AVERAGE('Interview Tracker'!J4:J33) | E8: Pain: Resume Formatting Count | F8: ==COUNTIF('Interview Tracker'!H4:H33, "Resume Formatting")
B9: Average Switching Probability (1-5) | C9: ==AVERAGE('Interview Tracker'!L4:L33) | E9: Pain: Slow Search Count | F9: ==COUNTIF('Interview Tracker'!H4:H33, "Slow Search")
B10: Total Committed Pilots | C10: ==COUNTIF('Interview Tracker'!Q4:Q33, "Committed") | E10: Pain: Invoicing / ATS Split Count | F10: ==COUNTIF('Interview Tracker'!H4:H33, "Invoicing")
B11: Average Willingness to Pay | C11: ==AVERAGEIF('Interview Tracker'!P4:P33, ">0") | E11: Pain: Data Security Count | F11: ==COUNTIF('Interview Tracker'!H4:H33, "Data Security")
B13: HOW TO INTERPRET THIS DASHBOARD:
B14: • Total Interviews Tracked: Shows how many of your 30 target interviews you have completed.
B15: • High Validation Leads: Indicates the number of leads that scored >= 75. A high percentage (e.g. >50%) represents strong PMF signals.
B16: • Segment Analysis: Focus your early sales outreach and product releases on the customer segment and pain point that have the highest frequency count.
